{
  "variant": "frozen",
  "null_kind": "plug_in_at_w_hat",
  "t_obs": 1348.6861098338268,
  "L_den_obs": 129302.21384406122,
  "L_num_obs": 128627.8707891443,
  "n_toys": 100,
  "toy_t_mean": 82.04777400128863,
  "toy_t_median": 79.77472269580176,
  "toy_t_std": 12.545712715390797,
  "n_toys_ge_obs": 0,
  "p_value_addone": 0.009900990099009901,
  "n_toys_with_negative_t": 0,
  "obs_den_grad_norm": 0.0,
  "obs_num_grad_norm": 8.922609812319217e-06,
  "obs_den_n_eval": 1,
  "obs_num_n_eval": 6,
  "obs_den_converged": true,
  "obs_num_converged": true,
  "obs_den_hit_max_iter": false,
  "obs_num_hit_max_iter": false,
  "toy_n_unconverged_den": 0,
  "toy_n_unconverged_num": 0,
  "toy_n_hit_max_iter_den": 0,
  "toy_n_hit_max_iter_num": 0,
  "toy_max_grad_norm_den": 0.0,
  "toy_max_grad_norm_num": 6.650626873239551e-05,
  "M_pert": 80,
  "pert_sigma": 0.1,
  "lam_ridge_pert": 0.001,
  "max_iter": 500,
  "tol": 1e-09
}